<?xml version="1.0" encoding="UTF-8"?>
<!DOCTYPE mapper PUBLIC "-//mybatis.org//DTD Mapper 3.0//EN"
 "http://mybatis.org/dtd/mybatis-3-mapper.dtd">
<mapper namespace="com.kim.app.model.movie.MybatisMovieDAO">

	<select id="selectAllm" resultType="MovieVO">
		select * from movie order by ratingavg desc limit #{start}, #{perPage}
	</select>

	<select id="selectAll" resultType="MovieVO">
		select * from movie where 1 = 1
		<choose>
			<when test="mtype==null or mtype.equals('')">
				<choose>
					<when test="search==null or search.equals('')">
						and 1 = 1
					</when>
					<otherwise>
						and title LIKE CONCAT('%', #{search}, '%')
					</otherwise>
				</choose>
			</when>
			<otherwise>
				<choose>
					<when test="search==null or search.equals('')">
						and mtype = #{mtype}
					</when>
					<otherwise>
						and mtype = #{mtype} and title LIKE CONCAT('%',	#{search}, '%')
					</otherwise>
				</choose>
			</otherwise>
		</choose>
		order by title asc limit #{start}, #{perPage}
	</select>

	<select id="mpk" resultType="MovieVO">
		select mpk from movie
	</select>
	
	<select id="selectOne" resultType="MovieVO">
		select * from movie where mpk = #{mpk}
	</select>
	
	<select id="count" resultType="int">
		select count(*) from movie
	</select>
	
	<select id="selectRand" resultType="MovieVO">
		select * from movie
	</select>

	<insert id="insert">
		insert into movie(mpk, title, content, mtype,mdate,filename) values (#{mpk},#{title},#{content},#{mtype},date_format(#{mdate},'%Y-%m-%d'),#{fileupload})
	</insert>

	<update id="update">
		update movie set title  = #{title}, content = #{content}, mtype = #{mtype}, mdate = date_format(#{mdate},'%Y-%m-%d'), filename = #{fileupload}  where mpk = #{mpk}
	</update>

	<delete id="delete">
		delete from movie where mpk = #{mpk}
	</delete>
	
	<delete id="rdelete">
		update movie set title  = #{title}, content = #{content}, mtype = #{mtype}, mdate = date_format(#{mdate},'%Y-%m-%d'), filename = #{filename}  where mpk = #{mpk}
	</delete>
</mapper>
